stups_cli/__init__.py
stups_cli/__main__.py
stups_cli/config.py
stups_cli_support-1.1.22.dist-info/LICENSE
stups_cli_support-1.1.22.dist-info/METADATA
stups_cli_support-1.1.22.dist-info/WHEEL
stups_cli_support-1.1.22.dist-info/entry_points.txt
stups_cli_support-1.1.22.dist-info/top_level.txt
stups_cli_support-1.1.22.dist-info/RECORD
