Metadata-Version: 2.1
Name: stups-cli-support
Version: 1.1.22
Summary: STUPS CLI support library
Home-page: https://github.com/zalando-stups/stups-cli-support
Author: Henning Jacobs
Author-email: henning@zalando.de
License: Apache License 2.0
Keywords: stups zalando cli
Platform: UNKNOWN
Classifier: Development Status :: 5 - Production/Stable
Classifier: Environment :: Console
Classifier: Intended Audience :: Developers
Classifier: Intended Audience :: System Administrators
Classifier: License :: OSI Approved :: Apache Software License
Classifier: Operating System :: POSIX :: Linux
Classifier: Programming Language :: Python
Classifier: Programming Language :: Python :: 3.7
Classifier: Programming Language :: Python :: 3.8
Classifier: Programming Language :: Python :: 3.9
Classifier: Programming Language :: Python :: Implementation :: CPython
Requires-Dist: clickclick (>=0.11)
Requires-Dist: PyYAML
Requires-Dist: dnspython (>=1.15.0)
Requires-Dist: requests
